neoscore/__init__.py
neoscore/common.py
neoscore/core/README.md
neoscore/core/__init__.py
neoscore/core/break_hint.py
neoscore/core/break_opportunity.py
neoscore/core/brush.py
neoscore/core/brush_pattern.py
neoscore/core/color.py
neoscore/core/directions.py
neoscore/core/document.py
neoscore/core/env.py
neoscore/core/exceptions.py
neoscore/core/flowable.py
neoscore/core/font.py
neoscore/core/glyph_info.py
neoscore/core/has_music_font.py
neoscore/core/image.py
neoscore/core/key_event.py
neoscore/core/layout_controllers.py
neoscore/core/math_helpers.py
neoscore/core/mouse_event.py
neoscore/core/music_char.py
neoscore/core/music_font.py
neoscore/core/music_path.py
neoscore/core/music_text.py
neoscore/core/neoscore.py
neoscore/core/page.py
neoscore/core/page_overlays.py
neoscore/core/page_supplier.py
neoscore/core/painted_object.py
neoscore/core/paper.py
neoscore/core/path.py
neoscore/core/path_element.py
neoscore/core/pen.py
neoscore/core/pen_cap_style.py
neoscore/core/pen_join_style.py
neoscore/core/pen_pattern.py
neoscore/core/point.py
neoscore/core/positioned_object.py
neoscore/core/propagating_thread.py
neoscore/core/raw_music_char.py
neoscore/core/rect.py
neoscore/core/repeating_music_text_line.py
neoscore/core/rich_text.py
neoscore/core/smufl.py
neoscore/core/spanner.py
neoscore/core/spanner_2d.py
neoscore/core/text.py
neoscore/core/text_alignment.py
neoscore/core/units.py
neoscore/interface/README.md
neoscore/interface/__init__.py
neoscore/interface/app_interface.py
neoscore/interface/brush_interface.py
neoscore/interface/font_interface.py
neoscore/interface/image_interface.py
neoscore/interface/invisible_object_interface.py
neoscore/interface/path_interface.py
neoscore/interface/pen_interface.py
neoscore/interface/positioned_object_interface.py
neoscore/interface/qt/README.md
neoscore/interface/qt/__init__.py
neoscore/interface/qt/converters.py
neoscore/interface/qt/file_paths.py
neoscore/interface/qt/hashing.py
neoscore/interface/qt/main_window.py
neoscore-0.1.16.dist-info/LICENSE.txt
neoscore-0.1.16.dist-info/METADATA
neoscore-0.1.16.dist-info/WHEEL
neoscore-0.1.16.dist-info/RECORD
