Metadata-Version: 2.1
Name: neoscore
Version: 0.1.16
Summary: A graphical musical notation library
Home-page: https://neoscore.org
License: BSD-3-Clause
Author: Andrew Yoon
Author-email: andrew@nothing-to-say.org
Requires-Python: >=3.7,<4.0
Classifier: License :: OSI Approved :: BSD License
Classifier: Programming Language :: Python :: 3
Classifier: Programming Language :: Python :: 3.7
Classifier: Programming Language :: Python :: 3.8
Classifier: Programming Language :: Python :: 3.9
Classifier: Programming Language :: Python :: 3.10
Classifier: Programming Language :: Python :: 3.11
Classifier: Programming Language :: Python :: 3.12
Classifier: Topic :: Multimedia :: Graphics
Requires-Dist: PyQt5 (>=5.15.6,<6.0.0)
Requires-Dist: backports.cached-property (==1.0.2)
Requires-Dist: img2pdf (==0.4.4)
Requires-Dist: pyqt5-qt5 (==5.15.2)
Requires-Dist: sortedcontainers (==2.4.0)
Requires-Dist: typing_extensions (>=4,<5)
Project-URL: Bug Tracker, https://github.com/DigiScore/neoscore/issues
Project-URL: Repository, https://github.com/DigiScore/neoscore
